CHANGELOG.txt
LICENCE.txt
MANIFEST.in
README.txt
setup.py
dist/mathgroup11-0.0.1/CHANGELOG.txt
dist/mathgroup11-0.0.1/LICENCE.txt
dist/mathgroup11-0.0.1/README.txt
dist/mathgroup11-0.0.1/setup.py
dist/mathgroup11-0.0.1/mathgroup11/__init__.py
dist/mathgroup11-0.0.1/mathgroup11.egg-info/SOURCES.txt
dist/mathgroup11-0.0.1/mathgroup11.egg-info/dependency_links.txt
dist/mathgroup11-0.0.1/mathgroup11.egg-info/top_level.txt
mathgroup11/__init__.py
mathgroup11.egg-info/PKG-INFO
mathgroup11.egg-info/SOURCES.txt
mathgroup11.egg-info/dependency_links.txt
mathgroup11.egg-info/top_level.txt