Metadata-Version: 2.1
Name: mathgroup11
Version: 0.0.3
Summary: This is a basic computational support library 
Home-page: 
Author: VuDo
Author-email: dophuvu016@gmail.com
License: MIT
Keywords: math
Classifier: Development Status :: 5 - Production/Stable
Classifier: Intended Audience :: Education
Classifier: Operating System :: Microsoft :: Windows :: Windows 10
Classifier: License :: OSI Approved :: MIT License
Classifier: Programming Language :: Python :: 3
License-File: LICENCE.txt
